{
  "id": "crawl-безоплатна-правнича-допомога-mnd8i32h",
  "category": "info",
  "tags": [
    "info",
    "послуги",
    "бюджет",
    "ВПО",
    "ветерани",
    "правова допомога"
  ],
  "title": "Безоплатна правнича допомога",
  "content": "Безоплатна правнича допомога\n \n\n \n\n \n\nВ Україні можна отримати юридичні послуги безоплатно. Їх надає, зокрема, система безоплатної правничої допомоги (БПД).\n\nСистема БПД має мережу точок доступу до правничої допомоги по всій Україні та надає правові консультації телефоном та онлайн.\n\nНадання правничих послуг гарантується Законом України «Про безоплатну правничу допомогу» та повністю фінансується за кошти Державного бюджету України. \n\nПослуги, які надає система БПД\n\n \n Консультації юристів з правових питань, допомога зі складенням правових документів (крім документів до суду) — надаються безоплатно усім.\n \n \n Допомога із зверненням до суду (представництво інтересів, складення процесуальних документів) — надаються категоріям громадян, визначених у статті 14 Закону України  «Про безоплатну правничу допомогу», зокрема: \n \n\n⦁ людям з інвалідністю\n\n⦁ людям з низьким доходом\n\n⦁ ВПО\n\n⦁ дітям \n\n⦁ ветеранам війни\n\n⦁ членам сімей загиблих ветеранів, Захисників і Захисниць України\n\n⦁ постраждали від домашнього насильства\n\n⦁         затриманим, підозрюваним, обвинуваченим, засудженим\n\n⦁         іншим\n\nДетальніше: https://legalaid.gov.ua/kliyentam/pro-bezoplatnu-pravovu-dopomogu-bpd/\n\nЯк звернутися до системи БПД: https://legalaid.gov.ua/kliyentam/yak-otrymaty-bpd/",
  "metadata": {
    "source": "https://zhovtanetska-gromada.gov.ua/bezoplatna-pravnicha-dopomoga-10-40-55-30-05-2024",
    "date": "2026-03-30",
    "updated": "2026-03-30"
  }
}