{
  "id": "crawl-рішення-сесії-сільської-ради-1-93-рішення-58-сесії-від-18-12-mnd8jwzf",
  "category": "regulations",
  "tags": [
    "regulations",
    "бюджет",
    "виконком",
    "комунальне"
  ],
  "title": "Рішення сесії сільської ради №1/93 «Рішення 58 сесії від 18.12.2025 р.»",
  "content": "Рішення сесії сільської ради №1/93 «Рішення 58 сесії від 18.12.2025 р.»\n\n \n Кількість переглядів: 109\n \n \n \n \n \n \n \n\n \n \n \n Властивість\n Значення\n \n \n \n \n Скликання:\n VIII скликання\n \n \n Сесія:\n 58 сесія 18.12.2025 року\n \n \n Тип документу:\n Рішення сесії сільської ради\n \n \n Дата:\n 18.12.2025\n \n \n Номер документу:\n 1/93\n \n \n Назва документу:\n Рішення 58 сесії від 18.12.2025 р.\n \n \n Прикріплені файли:\n \n \n \n \n \n \n \n\n \n Про затвердження порядку денного 58-ої сесії сільської ради\n \n \n Про внесення змін та доповнень до рішення Жовтанецької сільської ради від 19.12.2024 року №27 «Про місцевий бюджет Жовтанецької сільської ради на 2025 рік»\n \n \n Про внесення змін до Програм\n \n \n Про внесення змін та доповнень до рішення Жовтанецької сільської ради від 19.12.2024 року №27 «Про місцевий бюджет Жовтанецької сільської ради на 2025 рік» \n \n \n Про внесення змін до Програм \n \n \n Про виділення коштів\n \n \n Про внесення змін до договорів про міжбюджетні трансферти (субвенції) та затвердження договорів про міжбюджетні трансферти (субвенцію)\n \n \n Про затвердження рішень виконавчого комітету Жовтанецької сільської ради  виданих в міжсесійний період\n \n \n Про внесення змін до фінансового плану підприємства на 2025 рік \n \n\n \n Про затвердження Програми фінансового забезпечення представницьких витрат, пов’язаних із діяльністю Жовтанецької сільської  ради на  2026 рік \n \n \n Про затвердження Програми фінансової підтримки комунального некомерційного підприємства «Центр первинної медико-санітарної допомоги» Жовтанецької сільської ради Львівської області на 2026 рік\n \n \n Про затвердження Програми безоплатного та пільгового відпуску лікарських засобів за рецептами лікарів у разі амбулаторного лікування окремих груп населення та за певними категоріями захворювань на 2026 рік  \n \n \n Про затвердження Програми «Компенсація пільгового проїзду окремих категорій громадян на 2026 рік» \n \n \n Про затвердження Програми відшкодування компенсації за перевезення окремих пільгових категорій громадян на приміських маршрутах загального користування автомобільним транспортом на 2026 рік\n \n \n Про затвердження Програми компенсації фізичним особам, які надають соціальні послуги з догляду на непрофесійній основі на 2026 рік\n \n \n Про затвердження Цільової програми проведення громадських робіт Жовтанецької сільської ради на 2026 рік \n \n \n Про затвердження Програми соціального захисту окремих категорій населення Жовтанецької сільської ради на 2026 рік\n \n \n Про затвердження Програми соціального захисту військовослужбовців, осіб які захищали територіальну цілісність України і брали безпосередню участь у здійснені заходів із забезпечення національної безпеки і оборони, відсічі і стримуванні збройної агресії російської федерації та членів їх сімей на 2026 рік \n \n \n Про затвердження Програми та Порядку безоплатного поховання загиблих (померлих) військовослужбовців, учасників бойових дій внаслідок російської агресії проти України  на 2026 рік\n \n \n Про затвердження Програми розвитку культури Жовтанецької сільської ради на 2026 рік\n \n \n Про затвердження Комплексної Програми розвитку фізичної культури та спорту Жовтанецької сільської ради на 2026 рік \n \n \n Про затвердження Комплексної програми благоустрою та впорядкування території населених пунктів Жовтанецької сільської ради на 2026 рік\n \n \n Про затвердження Комплексної програми ремонту та утримання доріг комунальної власності в населених пунктах Жовтанецької сільської ради на 2026 рік \n \n \n Про затвердження Програми по запобіганню і ліквідації надзвичайних ситуацій та наслідків стихійного лиха і оперативне реагування на них у Жовтанецькій сільській раді на 2026 рік\n \n \n Про затвердження Програми «Безпечна громада на 2026 рік» Жовтанецької сільської ради  \n \n \n Про затвердження Програми розвитку освіти Жовтанецької територіальної громади на 2026-2028 роки, Додаток 1, Додаток 2\n \n \n Про затвердження Програми організація харчування учнів та дошкільнят закладів загальної середньої та дошкільної освіти Жовтанецької сільської ради на 2026 рік \n \n \n Про затвердження Програми «Шкільний автобус» Жовтанецької сільської ради на 2026 рік\n \n \n Про затвердження Програми підтримки обдарованих дітей Жовтанецької територіальної громади на 2026  рік  \n \n \n Про  затвердження Програми надання одноразової допомоги дітям-сиротам і дітям, позбавленим батьківського піклування після досягнення 18-річного віку на 2026 рік\n \n \n Про надання грошової компенсації за придбання спортивної форми дітям-сиротам і дітям, позбавленим батьківського піклування, які навчаються у закладах загальної середньої освіти Жовтанецької сільської ради \n \n \n Про організацію та встановлення батьківської плати за харчування дітей у ЗДО Жовтанецької сільської ради  на 2026 рік\n \n \n Про організацію та встановлення вартості харчування учнів та вихованців ЗЗСО Жовтанецької сільської ради на 2026 рік \n \n \n Про затвердження договорів про міжбюджетні трансферти (субвенції)\n \n \n Про місцевий бюджет Жовтанецької сільської ради на 2026 рік, Додаток 1, Додаток 2, Додаток 3, Додаток 4, Додаток 5, Додаток 6, Пояснююча\n \n \n Про затвердження структури та загальної чисельності апарату Жовтанецької сільської ради, Додаток\n \n \n Про затвердження структури та загальної чисельності фінансового відділу Жовтанецької сільської ради на 2026 рік, Додаток \n \n \n Про затвердження структури та загальної чисельності відділу освіти Жовтанецької сільської ради \n \n \n Про затвердження структури та загальної чисельності Служби у справах дітей Жовтанецької сільської ради Львівського району Львівської області на 2026 рік, Додаток\n \n \n Про затвердження структури та загальної чисельності Комунального закладу «Центр надання соціальних послуг» Жовтанецької сільської ради Львівського району Львівської області на 2026 рік, Додаток \n \n \n Про внесення змін та затвердження штатної чисельності місцевої пожежної охорони Жовтанецької сільської ради Львівського району Львівської області\n \n \n Про затвердження штатних розписів по Народних домах Жовтанецької сільської ради на 2026 рік, Додаток\n \n \n Про затвердження структури та штатної чисельності Комунального закладу «Центральна сільська публічна бібліотека» Жовтанецької сільської ради Львівського району Львівської області на 2026 рік, Додаток\n \n \n Про створення інклюзивної групи у Ременівському ЗДО «Зернятко»\n \n \n Про затвердження структури та штатної чисельності працівників закладів освіти Жовтанецької сільської ради \n \n \n Про плановий контингент учнів та встановлення розміру батьківської плати за навчання у Комунальному закладі «Жовтанецька школа мистецтв» Жовтанецької сільської ради Львівського району Львівської області\n \n \n Про затвердження фінансових планів підприємств на 2026 рік\n \n \n Про встановлення умов оплати праці сільському голові на 2026 рік\n \n \n Про встановлення умов оплати праці першому заступнику сільського голови на 2026 рік\n \n \n Про встановлення умов оплати праці секретарю сільської ради на 2026 рік\n \n \n Про затвердження кошторису видатків на утримання апарату та виконавчих органів Жовтанецької сільської ради на 2026 рік, Додаток, Додаток\n \n \n Про встановлення розміру кошторисної заробітної плати, який враховується при визначенні вартості будівництва (нового будівництва, реконструкції, реставрації, капітального ремонту, технічного переоснащення) об’єктів, що споруджуються із залученням бюджетних коштів, коштів державних і комунальних підприємств, установ та організацій, а також кредитів, наданих під державні гарантії\n \n \n Про надання дозволу відділу освіти на укладання Договору оренди \n \n \n Про списання основних засобів, інших необоротних матеріальних активів\n \n \n Про збільшення вартості основного засобу\n \n \n Про затвердження Плану роботи Жовтанецької сільської ради на 2026 рік\n \n \n Про внесення змін до рішення сесії Жовтанецької сільської ради від 20 жовтня 2025 року № 13\n \n \n Про затвердження Методики розрахунку орендної плати за нерухоме комунальне майно територіальної громади Жовтанецької сільської ради для визначеного кола орендарів\n \n \n Про затвердження проекту землеустрою щодо відведення земельної ділянки та продаж права її оренди на земельних торгах у формі електронного аукціону\n \n \n Про затвердження проекту землеустрою щодо відведення земельної ділянки та продаж права її оренди на земельних торгах у формі електронного аукціону\n \n \n Про включення земельної ділянки до переліку ділянок для підготовки Лотів для продажу цієї земельної ділянки на земельних торгах (електронних аукціонах) та надання дозволу на виготовлення проекту відведення даної ділянки\n \n \n Про внесення змін в рішення сесії Жовтанецької сільської ради за №32 від 20 жовтня 2025 року «Про надання дозволу на розроблення технічної документації з нормативної грошової оцінки земельних ділянок в межах Жовтанецької сільської ради»\n \n \n Про надання земельної ділянки в оренду гр. Кук Н.Т. для городництва\n \n \n Про надання земельної ділянки в оренду гр. Кук Г.М. для городництва\n \n \n Про затвердження технічної документації із землеустрою щодо інвентаризації земельної ділянки\n \n \n Про розгляд заяви гр. Макало А.С.\n \n \n Про врегулювання питання щодо відшкодування втрат до місцевого бюджету  від недоотримання коштів за фактичне використання земельних ділянок та оформлення правовстановлюючих документів на ці ділянки\n \n \n Про надання дозволу на розробку проекту відведення земельної ділянки в с. Новий Став\n \n \n Про надання дозволу на розробку проекту відведення земельної ділянки в с. Горпин\n \n \n Про надання дозволу на розробку проекту відведення земельної ділянки в с. Жовтанці\n \n \n Про надання дозволу на розробку проекту відведення земельної ділянки в с. Жовтанці\n \n \n Про надання дозволу на розробку проекту відведення земельної ділянки в с. Жовтанці\n \n \n Про надання дозволу на розробку проекту відведення земельної ділянки в с. Жовтанці\n \n \n Про надання дозволу на розробку проекту відведення земельної ділянки в с. Велике Колодно\n \n \n Про зміну цільового призначення земельної ділянки\n \n \n Про передачу в оренду земельної ділянки гр. Кушпіту М.І.\n \n \n Про зняття з користування земельної ділянки гр. Плюхи Г.",
  "metadata": {
    "source": "https://zhovtanetska-gromada.gov.ua/docs/2218892",
    "date": "2026-03-30",
    "updated": "2026-03-30",
    "files": [
      {
        "name": "Про внесення змін та доповнень до рішення Жовтанецької сільської ради від 19.12.2024 року №27 «Про місцевий бюджет Жовтанецької сільської ради на 2025 рік»",
        "url": "https://rada.info/upload/users_files/04374039/ee139e1b6474deef739d60380d2a59eb.doc"
      },
      {
        "name": "Про внесення змін до Програм",
        "url": "https://rada.info/upload/users_files/04374039/86705eeed5a1e40a90e72072c5b838b4.doc"
      },
      {
        "name": "Про внесення змін та доповнень до рішення Жовтанецької сільської ради від 19.12.2024 року №27 «Про місцевий бюджет Жовтанецької сільської ради на 2025 рік»",
        "url": "https://rada.info/upload/users_files/04374039/7006a516ebfe8bef718ef560e7dd3c6e.doc"
      },
      {
        "name": "Про внесення змін до Програм",
        "url": "https://rada.info/upload/users_files/04374039/edf07526e2e65e2a5bfb504d6cdf928c.doc"
      },
      {
        "name": "Про виділення коштів",
        "url": "https://rada.info/upload/users_files/04374039/0838dec4fdf65189a48f7174be21932d.doc"
      },
      {
        "name": "Про внесення змін до договорів про міжбюджетні трансферти (субвенції) та затвердження договорів про міжбюджетні трансферти (субвенцію)",
        "url": "https://rada.info/upload/users_files/04374039/e5d58014c2512dff2a90663222b5a44a.doc"
      },
      {
        "name": "Про затвердження рішень виконавчого комітету Жовтанецької сільської ради  виданих в міжсесійний період",
        "url": "https://rada.info/upload/users_files/04374039/16415630c78c1bc5bb7be72da6118aa5.doc"
      },
      {
        "name": "Про внесення змін до фінансового плану підприємства на 2025 рік",
        "url": "https://rada.info/upload/users_files/04374039/2233dfdf49535711466dbc0bbd3875cf.doc"
      },
      {
        "name": "Про затвердження Програми фінансового забезпечення представницьких витрат, пов’язаних із діяльністю Жовтанецької сільської  ради на  2026 рік",
        "url": "https://rada.info/upload/users_files/04374039/5fe24ef2650dfcc4a219fa64143ed465.doc"
      },
      {
        "name": "Про затвердження Програми фінансової підтримки комунального некомерційного підприємства «Центр первинної медико-санітарної допомоги» Жовтанецької сільської ради Львівської області на 2026 рік",
        "url": "https://rada.info/upload/users_files/04374039/c1e220fbfd656c2ba937e60f2978a16d.doc"
      },
      {
        "name": "Про затвердження Програми безоплатного та пільгового відпуску лікарських засобів за рецептами лікарів у разі амбулаторного лікування окремих груп населення та за певними категоріями захворювань на 2026 рік",
        "url": "https://rada.info/upload/users_files/04374039/8bbb160e29f1f1fca638a9993e3d04b0.doc"
      },
      {
        "name": "Про затвердження Програми «Компенсація пільгового проїзду окремих категорій громадян на 2026 рік»",
        "url": "https://rada.info/upload/users_files/04374039/2f7f23ce6b3b7a1331537bd09e02fe8c.doc"
      },
      {
        "name": "Про затвердження Програми відшкодування компенсації за перевезення окремих пільгових категорій громадян на приміських маршрутах загального користування автомобільним транспортом на 2026 рік",
        "url": "https://rada.info/upload/users_files/04374039/1214b7d9c1618841589ed47eb16d5868.doc"
      },
      {
        "name": "Про затвердження Програми компенсації фізичним особам, які надають соціальні послуги з догляду на непрофесійній основі на 2026 рік",
        "url": "https://rada.info/upload/users_files/04374039/3cbb00c211a2eefaa3b12e6ecaf13fbf.doc"
      },
      {
        "name": "Про затвердження Цільової програми проведення громадських робіт Жовтанецької сільської ради на 2026 р",
        "url": "https://rada.info/upload/users_files/04374039/78020208620dc00039610f86dccb95a3.doc"
      },
      {
        "name": "Про затвердження Програми соціального захисту окремих категорій населення Жовтанецької сільської ради на 2026 рік",
        "url": "https://rada.info/upload/users_files/04374039/a28910a1b878fc82ffa152dbe2c0b900.doc"
      },
      {
        "name": "Про затвердження Програми соціального захисту військовослужбовців, осіб які захищали територіальну цілісність України і брали безпосередню участь у здійснені заходів із забезпечення національної безпеки і оборони, відсічі і стримуванні збройної агресії російської федерації та членів їх сімей на 2026 рік",
        "url": "https://rada.info/upload/users_files/04374039/9936791496f0d2f0e65584ec2bdd5a7a.doc"
      },
      {
        "name": "Про затвердження Програми та Порядку безоплатного поховання загиблих (померлих) військовослужбовців, учасників бойових дій внаслідок російської агресії проти України  на 2026 рік",
        "url": "https://rada.info/upload/users_files/04374039/32b15ae796366a98ef8cc80a289fca25.docx"
      },
      {
        "name": "Про затвердження Програми розвитку культури Жовтанецької сільської ради на 2026 рік",
        "url": "https://rada.info/upload/users_files/04374039/da0f3d7010f0eb38d98f649e6dc9c743.doc"
      },
      {
        "name": "Про затвердження Комплексної Програми розвитку фізичної культури та спорту Жовтанецької сільської ради на 2026 рік",
        "url": "https://rada.info/upload/users_files/04374039/b4b62d53e7e93e166cc3b9d9f570e139.doc"
      },
      {
        "name": "Про затвердження Комплексної програми благоустрою та впорядкування території населених пунктів Жовтанецької сільської ради на 2026 рік",
        "url": "https://rada.info/upload/users_files/04374039/a1fd68d51c5a77619570ae2ec0116c15.doc"
      },
      {
        "name": "Про затвердження Комплексної програми ремонту та утримання доріг комунальної власності в населених пунктах Жовтанецької сільської ради на 2026 рік",
        "url": "https://rada.info/upload/users_files/04374039/5d8aedda1b10f1f27ebdae3f490ad1ff.doc"
      },
      {
        "name": "Про затвердження Програми по запобіганню і ліквідації надзвичайних ситуацій та наслідків стихійного лиха і оперативне реагування на них у Жовтанецькій сільській раді на 2026 рік",
        "url": "https://rada.info/upload/users_files/04374039/6ed2e874eb59d2d3db3a61b8eba4e6ca.doc"
      },
      {
        "name": "Про затвердження Програми «Безпечна громада на 2026 рік» Жовтанецької сільської ради",
        "url": "https://rada.info/upload/users_files/04374039/f6e7677e811c3162a2c7641c83f4c95f.docx"
      },
      {
        "name": "Про затвердження Програми розвитку освіти Жовтанецької територіальної громади на 2026-2028 роки",
        "url": "https://rada.info/upload/users_files/04374039/1f0b00d6febdf9630ec2bd95943f212b.doc"
      },
      {
        "name": "Додаток 1",
        "url": "https://rada.info/upload/users_files/04374039/4ca26157b894ec5c8e0b75a7cff56f11.doc"
      },
      {
        "name": "Додаток 2",
        "url": "https://rada.info/upload/users_files/04374039/ac83aa6018a96f680d8f293b5bb7fe4a.doc"
      },
      {
        "name": "Про затвердження Програми організація харчування учнів та дошкільнят закладів загальної середньої та дошкільної освіти Жовтанецької сільської ради на 2026 рік",
        "url": "https://rada.info/upload/users_files/04374039/1040197ad6ee6a41db28f1e3c06900da.doc"
      },
      {
        "name": "Про затвердження Програми «Шкільний автобус» Жовтанецької сільської ради на 2026 рік",
        "url": "https://rada.info/upload/users_files/04374039/7f94c4de9542be618f8303d9c849a0c5.doc"
      },
      {
        "name": "Про затвердження Програми підтримки обдарованих дітей Жовтанецької територіальної громади на 2026  рік",
        "url": "https://rada.info/upload/users_files/04374039/f81f9abcec401be87954e03045b4aaa3.doc"
      },
      {
        "name": "Про  затвердження Програми надання одноразової допомоги дітям-сиротам і дітям, позбавленим батьківського піклування після досягнення 18-річного віку на 2026 рік",
        "url": "https://rada.info/upload/users_files/04374039/dea010185ef4a8e2ea142fbd59f46f00.docx"
      },
      {
        "name": "Про надання грошової компенсації за придбання спортивної форми дітям-сиротам і дітям, позбавленим батьківського піклування, які навчаються у закладах загальної середньої освіти Жовтанецької сільської ради",
        "url": "https://rada.info/upload/users_files/04374039/ee147793a68f3957c8e66e171df15ad8.doc"
      },
      {
        "name": "Про організацію та встановлення батьківської плати за харчування дітей у ЗДО Жовтанецької сільської ради  на 2026 рік",
        "url": "https://rada.info/upload/users_files/04374039/6bf0237cbf3139e0a901347fca2550fe.doc"
      },
      {
        "name": "Про організацію та встановлення вартості харчування учнів та вихованців ЗЗСО Жовтанецької сільської ради на 2026 рік",
        "url": "https://rada.info/upload/users_files/04374039/e84bb74aea1d2bc4c6b814fe6678cc63.doc"
      },
      {
        "name": "Про затвердження договорів про міжбюджетні трансферти (субвенції)",
        "url": "https://rada.info/upload/users_files/04374039/32e019aa157c7f9752aa1bdddcb9bb56.doc"
      },
      {
        "name": "Про місцевий бюджет Жовтанецької сільської ради на 2026 рік",
        "url": "https://rada.info/upload/users_files/04374039/12394e0e18168fa26167a0352b91229f.docx"
      },
      {
        "name": "Додаток 1",
        "url": "https://rada.info/upload/users_files/04374039/4fa88656199c57396c3af32e998292c5.xlsx"
      },
      {
        "name": "Додаток 2",
        "url": "https://rada.info/upload/users_files/04374039/f5fb8c89d33417412da2d201c7192139.xlsx"
      },
      {
        "name": "Додаток 3",
        "url": "https://rada.info/upload/users_files/04374039/862b6a8765f666fc2412f1ec4ca11d17.xlsx"
      },
      {
        "name": "Додаток 4",
        "url": "https://rada.info/upload/users_files/04374039/073f4ffb615293be0b8e02dc7f2512d4.xls"
      },
      {
        "name": "Додаток 5",
        "url": "https://rada.info/upload/users_files/04374039/abf440f0569275d363aebc06d75edc01.xlsx"
      },
      {
        "name": "Додаток 6",
        "url": "https://rada.info/upload/users_files/04374039/84605869186e764a491cb276d798d07e.xls"
      },
      {
        "name": "Пояснююча",
        "url": "https://rada.info/upload/users_files/04374039/d03a6a176fc29dd4f0ce0b7b984a5044.docx"
      },
      {
        "name": "Про затвердження структури та загальної чисельності апарату Жовтанецької сільської ради",
        "url": "https://rada.info/upload/users_files/04374039/2ef1574b211890faf4586450e6723a03.docx"
      },
      {
        "name": "Додаток",
        "url": "https://rada.info/upload/users_files/04374039/15da81cbfd526c5ba2ccb6d9914b2b1a.xlsx"
      },
      {
        "name": "Про затвердження структури та загальної чисельності фінансового відділу Жовтанецької сільської ради на 2026 рік",
        "url": "https://rada.info/upload/users_files/04374039/f6ed5171f43c7ad2656513b8e79f8d25.doc"
      },
      {
        "name": "Додаток",
        "url": "https://rada.info/upload/users_files/04374039/f78bb4f9a5a36ac8c60811f1020c27a6.xlsx"
      },
      {
        "name": "Про затвердження структури та загальної чисельності відділу освіти Жовтанецької сільської ради",
        "url": "https://rada.info/upload/users_files/04374039/3c2315e234573b41da5004c6d3493df5.doc"
      },
      {
        "name": "Про затвердження структури та загальної чисельності Служби у справах дітей Жовтанецької сільської ради Львівського району Львівської області на 2026 рік",
        "url": "https://rada.info/upload/users_files/04374039/0c6d7d089db99cd05347a0b556a439cd.doc"
      },
      {
        "name": "Додаток",
        "url": "https://rada.info/upload/users_files/04374039/514a9d0c6b0fb9fe63becc2b7a118e2c.xlsx"
      },
      {
        "name": "Про затвердження структури та загальної чисельності Комунального закладу «Центр надання соціальних послуг» Жовтанецької сільської ради Львівського району Львівської області на 2026 рік",
        "url": "https://rada.info/upload/users_files/04374039/83ed756036145eebe5195fb2963577f7.doc"
      },
      {
        "name": "Додаток",
        "url": "https://rada.info/upload/users_files/04374039/1f5b2f718a973f30caa76e894fafd68e.xlsx"
      },
      {
        "name": "Про внесення змін та затвердження штатної чисельності місцевої пожежної охорони Жовтанецької сільської ради Львівського району Львівської област",
        "url": "https://rada.info/upload/users_files/04374039/c7705c08cc2f44a60bd1ab9d2f029a39.docx"
      },
      {
        "name": "Про затвердження штатних розписів по Народних домах Жовтанецької сільської ради на 2026 рік",
        "url": "https://rada.info/upload/users_files/04374039/af6c0bd3681797ee845362b287d66692.doc"
      },
      {
        "name": "Додаток",
        "url": "https://rada.info/upload/users_files/04374039/be54749b9e2bfb66184d1343c3394aa1.xlsx"
      },
      {
        "name": "Про затвердження структури та штатної чисельності Комунального закладу «Центральна сільська публічна бібліотека» Жовтанецької сільської ради Львівського району Львівської області на 2026 рік",
        "url": "https://rada.info/upload/users_files/04374039/954a4dedc634213ccb3f10226bff1167.doc"
      },
      {
        "name": "Додаток",
        "url": "https://rada.info/upload/users_files/04374039/9f43cd239a1fcf70d03ee2ce7f727826.xlsx"
      },
      {
        "name": "Про створення інклюзивної групи у Ременівському ЗДО «Зернятко»",
        "url": "https://rada.info/upload/users_files/04374039/35433261a99a6d199ad0d74bbab2600c.doc"
      },
      {
        "name": "Про затвердження структури та штатної чисельності працівників закладів освіти Жовтанецької сільської ради",
        "url": "https://rada.info/upload/users_files/04374039/bfed1f5887ef53125cdbb772aa315828.doc"
      },
      {
        "name": "Про плановий контингент учнів та встановлення розміру батьківської плати за навчання у Комунальному закладі «Жовтанецька школа мистецтв» Жовтанецької сільської ради Львівського району Львівської області",
        "url": "https://rada.info/upload/users_files/04374039/15a2dea4f99db53fc820d15f4b9ef15a.doc"
      },
      {
        "name": "Про затвердження фінансових планів підприємств на 2026 рік",
        "url": "https://rada.info/upload/users_files/04374039/88979a18ac9d0532344d5590abbf0aa7.doc"
      },
      {
        "name": "Про встановлення умов оплати праці сільському голові на 2026 рік",
        "url": "https://rada.info/upload/users_files/04374039/a3e1e2f88e4b157bea87b83b1d7449e3.doc"
      },
      {
        "name": "Про встановлення умов оплати праці першому заступнику сільського голови на 2026 рік",
        "url": "https://rada.info/upload/users_files/04374039/9b81af238069fcbfcc236f5ac2f7e683.doc"
      },
      {
        "name": "Про встановлення умов оплати праці секретарю сільської ради на 2026 рік",
        "url": "https://rada.info/upload/users_files/04374039/be26dd9dd77ca372b1c8d461d38e2c87.doc"
      },
      {
        "name": "Про затвердження кошторису видатків на утримання апарату та виконавчих органів Жовтанецької сільської ради на 2026 рік",
        "url": "https://rada.info/upload/users_files/04374039/f6f264492e288e91bbd50b5a152cc57b.doc"
      },
      {
        "name": "Додаток",
        "url": "https://rada.info/upload/users_files/04374039/52f1cf6b1663d5c3b3da132c80a57b25.xlsx"
      },
      {
        "name": "Додаток",
        "url": "https://rada.info/upload/users_files/04374039/9e9bfd8431d55d99953f086ea173d595.docx"
      },
      {
        "name": "Про встановлення розміру кошторисної заробітної плати, який враховується при визначенні вартості будівництва (нового будівництва, реконструкції, реставрації, капітального ремонту, технічного переоснащення) об’єктів, що споруджуються із залученням бюджетних коштів, коштів державних і комунальних підприємств, установ та організацій, а також кредитів, наданих під державні гарантії",
        "url": "https://rada.info/upload/users_files/04374039/fa18d43835d3472fd9c0c6cc05579a19.doc"
      },
      {
        "name": "Про надання дозволу відділу освіти на укладання Договору оренди",
        "url": "https://rada.info/upload/users_files/04374039/063dd0895abff7e27ef4b7964ee42fac.docx"
      },
      {
        "name": "Про списання основних засобів, інших необоротних матеріальних активів",
        "url": "https://rada.info/upload/users_files/04374039/d0ac6f456a9ad3b2bbc120b0047f9e1e.docx"
      },
      {
        "name": "Про збільшення вартості основного засобу",
        "url": "https://rada.info/upload/users_files/04374039/27e04f0688cac3c8f3117900cf6bc1af.docx"
      },
      {
        "name": "Про затвердження Плану роботи Жовтанецької сільської ради на 2026 рік",
        "url": "https://rada.info/upload/users_files/04374039/a717116c8507119f27eb6a653e21ab12.docx"
      },
      {
        "name": "Про внесення змін до рішення сесії Жовтанецької сільської ради від 20 жовтня 2025 року № 13",
        "url": "https://rada.info/upload/users_files/04374039/c5d61edbdcf21c21ffb44f5097139bcb.docx"
      },
      {
        "name": "Про затвердження Методики розрахунку орендної плати за нерухоме комунальне майно територіальної громади Жовтанецької сільської ради для визначеного кола орендарів",
        "url": "https://rada.info/upload/users_files/04374039/0c31bf5dafc76b6a1d2656fda827b53c.doc"
      },
      {
        "name": "Про затвердження проекту землеустрою щодо відведення земельної ділянки та продаж права її оренди на земельних торгах у формі електронного аукціону",
        "url": "https://rada.info/upload/users_files/04374039/60b3a009b49941ba308f053ca73a2ae2.doc"
      },
      {
        "name": "Про затвердження проекту землеустрою щодо відведення земельної ділянки та продаж права її оренди на земельних торгах у формі електронного аукціону",
        "url": "https://rada.info/upload/users_files/04374039/da207ef8a4733b7a66684548047e80e5.doc"
      },
      {
        "name": "Про включення земельної ділянки до переліку ділянок для підготовки Лотів для продажу цієї земельної ділянки на земельних торгах (електронних аукціонах) та надання дозволу на виготовлення проекту відведення даної ділянки",
        "url": "https://rada.info/upload/users_files/04374039/a997d26b98148839e4409fe399e6f004.doc"
      },
      {
        "name": "Про внесення змін в рішення сесії Жовтанецької сільської ради за №32 від 20 жовтня 2025 року «Про надання дозволу на розроблення технічної документації з нормативної грошової оцінки земельних ділянок в межах Жовтанецької сільської ради»",
        "url": "https://rada.info/upload/users_files/04374039/33709ea3f4c52bf3e75e8482a508c8e4.docx"
      },
      {
        "name": "Про надання земельної ділянки в оренду гр. Кук Н.Т. для городництва",
        "url": "https://rada.info/upload/users_files/04374039/41069ab941a6e7320a1355707551dbcc.doc"
      },
      {
        "name": "Про надання земельної ділянки в оренду гр. Кук Г.М. для городництва",
        "url": "https://rada.info/upload/users_files/04374039/c4d94e1e2bf0ae7d4037b6de8a010daf.doc"
      },
      {
        "name": "Про затвердження технічної документації із землеустрою щодо інвентаризації земельної ділянки",
        "url": "https://rada.info/upload/users_files/04374039/090c9cc2bf801ecf8db0c6af0845c870.doc"
      },
      {
        "name": "Про розгляд заяви гр. Макало А.С.",
        "url": "https://rada.info/upload/users_files/04374039/45b865ef1bb864b5ada595cc93c564a4.doc"
      },
      {
        "name": "Про врегулювання питання щодо відшкодування втрат до місцевого бюджету  від недоотримання коштів за фактичне використання земельних ділянок та оформлення правовстановлюючих документів на ці ділянки",
        "url": "https://rada.info/upload/users_files/04374039/f09f1ed7d906305b621d2df7e817992f.doc"
      },
      {
        "name": "Про надання дозволу на розробку проекту відведення земельної ділянки в с. Новий Став",
        "url": "https://rada.info/upload/users_files/04374039/baf0f778e07f6b09bee8c242dda713c4.doc"
      },
      {
        "name": "Про надання дозволу на розробку проекту відведення земельної ділянки в с. Горпин",
        "url": "https://rada.info/upload/users_files/04374039/dc74b5e957097e0fb349717cc12db984.doc"
      },
      {
        "name": "Про надання дозволу на розробку проекту відведення земельної ділянки в с. Жовтанці",
        "url": "https://rada.info/upload/users_files/04374039/af192ca82f387ccc5000349ba4d49f99.doc"
      },
      {
        "name": "Про надання дозволу на розробку проекту відведення земельної ділянки в с. Жовтанці",
        "url": "https://rada.info/upload/users_files/04374039/765e26d27cb5e84127c1080a01222b12.doc"
      },
      {
        "name": "Про надання дозволу на розробку проекту відведення земельної ділянки в с. Жовтанці",
        "url": "https://rada.info/upload/users_files/04374039/ef78b9bdaf19c4cd9ba86349692c7ffd.doc"
      },
      {
        "name": "Про надання дозволу на розробку проекту відведення земельної ділянки в с. Жовтанці",
        "url": "https://rada.info/upload/users_files/04374039/81df0f7c4864cf92498c7dc970a94dcd.doc"
      },
      {
        "name": "Про надання дозволу на розробку проекту відведення земельної ділянки в с. Велике Колодно",
        "url": "https://rada.info/upload/users_files/04374039/c4b84dc15600315f0fd03323ea0eafbe.doc"
      },
      {
        "name": "Про зміну цільового призначення земельної ділянки",
        "url": "https://rada.info/upload/users_files/04374039/014c16a91a4b74e2b12906c520b9ccf5.doc"
      },
      {
        "name": "Про передачу в оренду земельної ділянки гр. Кушпіту М.І.",
        "url": "https://rada.info/upload/users_files/04374039/87ac93132a460cabf6511f650e634aee.docx"
      },
      {
        "name": "Про зняття з користування земельної ділянки гр. Плюхи Г.А.",
        "url": "https://rada.info/upload/users_files/04374039/f884ab2cad235d05ba7ed1f099be0ab2.doc"
      },
      {
        "name": "Про надання дозволу на виготовлення технічної документації із землеустрою щодо встановлення (відновлення) меж земельної ділянки в натурі ( на місцевості )",
        "url": "https://rada.info/upload/users_files/04374039/9123939691c66da6f21ff44c276ff8e4.doc"
      },
      {
        "name": "Про надання дозволу на виготовлення технічної документації щодо встановлення (відновлення) меж земельної ділянки гр. Блощіцина В.В.",
        "url": "https://rada.info/upload/users_files/04374039/ce39c401da30d32396ae3e412cdcdebc.doc"
      },
      {
        "name": "Про надання дозволу на виготовлення технічної документації щодо встановлення  (відновлення) меж земельної ділянки гр. Блощіцина В.В.",
        "url": "https://rada.info/upload/users_files/04374039/279f8a547ad09ec170fb3fa9cc59cf39.doc"
      },
      {
        "name": "Про надання дозволу на виготовлення технічної документації щодо встановлення (відновлення) меж земельної ділянки гр. Василенко М.Я.",
        "url": "https://rada.info/upload/users_files/04374039/441d0196847b8723f38873b71070645c.doc"
      },
      {
        "name": "Про надання дозволу на виготовлення технічної документації щодо встановлення (відновлення) меж земельної ділянки гр. Гриців В.В.",
        "url": "https://rada.info/upload/users_files/04374039/2be812fa0fd6d0490b1dd24f5a6aed57.doc"
      },
      {
        "name": "Про надання дозволу на виготовлення технічної документації щодо встановлення (відновлення) меж земельної ділянки гр. Кіт Г.П.",
        "url": "https://rada.info/upload/users_files/04374039/f5a3245067b54787b9a676376578cc17.doc"
      },
      {
        "name": "Про надання дозволу на виготовлення технічної документації щодо встановлення (відновлення) меж земельної ділянки гр. Галушки П.С",
        "url": "https://rada.info/upload/users_files/04374039/31feac3621a16b5275ba8b94efd64cdc.doc"
      },
      {
        "name": "Про надання земельної ділянки у спільну сумісну власність",
        "url": "https://rada.info/upload/users_files/04374039/66fd8aaf8406cc881efe1cd18fc354d8.doc"
      },
      {
        "name": "Про надання земельних ділянок у власність",
        "url": "https://rada.info/upload/users_files/04374039/59d498d3f9bae7d23799b67ed4b18be8.doc"
      },
      {
        "name": "для будівництва житлового будинку господарських будівель і споруд",
        "url": "https://rada.info/upload/users_files/04374039/59d498d3f9bae7d23799b67ed4b18be8.doc"
      },
      {
        "name": "Про надання земельних ділянок у власність для ведення товарного сільськогосподарського виробництва",
        "url": "https://rada.info/upload/users_files/04374039/9e78f6d1627d62905d3aafd6db4d7ca0.doc"
      },
      {
        "name": "Про затвердження Акту комісії",
        "url": "https://rada.info/upload/users_files/04374039/aa65b134d544b29c8bab481c196052b6.docx"
      },
      {
        "name": "Про уточнення площ та конфігурації земельної ділянки",
        "url": "https://rada.info/upload/users_files/04374039/d4c5324709c112fc1d63b389431b901f.doc"
      },
      {
        "name": "Про уточнення площ та конфігурації земельної ділянки",
        "url": "https://rada.info/upload/users_files/04374039/05120b58c380db5945e5cfce3942d52b.doc"
      },
      {
        "name": "Про уточнення площ та конфігурації земельної ділянки",
        "url": "https://rada.info/upload/users_files/04374039/e0727766fdf20c7b34c64db3925990d5.doc"
      },
      {
        "name": "Про розгляд клопотання ТзОВ «Контінентал Фармерз Львів»",
        "url": "https://rada.info/upload/users_files/04374039/e51289b371603d35c43c5782f13a735f.doc"
      },
      {
        "name": "Про розгляд клопотання ТзОВ «Контінентал Фармерз Львів»",
        "url": "https://rada.info/upload/users_files/04374039/3c4349192fa41328ce46c368d9f56c9a.doc"
      },
      {
        "name": "Результати поіменного голосування 58 сесії 18.12.2025 року",
        "url": "https://rada.info/upload/users_files/04374039/786de17aee60409ecb39abab9cda0396.xlsx"
      }
    ],
    "tables": "1 tables"
  }
}